[1,["ecpdLyjvZBwrvm+cedCcQy","f7tCORIK9MY6ioAKXBckkK","907bJy3hJFg5nXXnMVJepf","19Km62o+pMsIBCELXsf1u0","05NL1NNuJC+bAyxrcyuVFx","a8rWUO2dtIC59l/RtfIjrn","83HhWajPFIq6aoX60gWqG6","b4+7+HK+NGyYua6CNAa3Fk","a8y//7uoFD5JJx3DIhtv04","e94+wn4gNEDqrlNPLlOw8t","9elDoIzT9Ig4DG8tZxKlSj","feY2UyaRpOWb74zsqRmt4U","4ekHtGvPBJN62vn8vIS2Y1","82AA8vsdhJ66JItcj7KJag","940VaDi3BAsrleWcpV3JKn","1cJU2RtLtE54uD9Kt2YygO","16MWVvjtxBzaKxk1qGiewq","132KgEEPhHeJ+lTFw9wsPA","55l6brz/VJDa6fNxW71JvP","16kWBybwVKL74RNUw7A6Om","51KEsQ95FNhaw9E5qwzf+r","1dc6KeaDhIfq3DpnUlgtfY","49NmeEN3lKD59QYirtA6Rk"],["node","_textureSetter","_spriteFrame","_N$normalSprite","_N$hoverSprite","scene","_parent"],["cc.SpriteFrame",["cc.Node",["_name","_id","_components","_contentSize","_trs","_parent","_children"],1,9,5,7,1,2],["cc.SceneAsset",["_name","asyncLoadAssets"],1],["cc.Canvas",["node","_designResolution"],3,1,5],["cc.Widget",["_alignFlags","node"],2,1],["cc.Sprite",["node","_materials","_spriteFrame"],3,1,3,6],["cc.Button",["_N$transition","node","_N$normalSprite","_N$hoverSprite"],2,1,6,6],["121064n04FOKJM24UIgmlpW",["node"],3,1],["7951aqej6RIYK6G54NPbsZA",["node"],3,1],["6708cIxPjJJo4CuKifu6/vg",["node"],3,1],["a16f0MIe79N0Y7O7RaxGIdS",["node"],3,1],["d8ccfxJ8IxOd51alxop7fAf",["node"],3,1],["cc.Scene",["_name","_children","_anchorPoint","_trs"],2,2,5,7],["cc.Camera",["_clearFlags","node"],2,1]],[[1,0,5,2,3,4,2],[5,0,1,2,1],[6,0,1,2,3,2],[2,0,1,3],[1,0,1,6,2,3,4,3],[1,0,5,2,3,2],[3,0,1,1],[4,0,1,2],[7,0,1],[8,0,1],[9,0,1],[10,0,1],[11,0,1],[12,0,1,2,3,2],[13,0,1,2]],[[[{"name":"04 white","rect":[214,172,596,56],"offset":[-448,0],"originalSize":[1920,400],"capInsets":[0,0,0,0]}],[0],0,[0],[1],[6]],[[[3,"shouYe",null],[4,"Canvas","a5esZu+45LA5mBpvttspPD",[-3,-4,-5,-6,-7,-8,-9],[[6,-1,[5,1920,1080]],[7,45,-2]],[5,1920,1080],[960,540,0,0,0,0,1,1,1,1]],[0,"01 white",1,[[1,-10,[2],3],[2,2,-11,4,5],[8,-12]],[5,771,58],[-440.302,-40,0,0,0,0,1,1,1,1]],[0,"02 white",1,[[1,-13,[6],7],[2,2,-14,8,9],[9,-15]],[5,713,58],[-468.663,-130,0,0,0,0,1,1,1,1]],[0,"03 white",1,[[1,-16,[10],11],[2,2,-17,12,13],[10,-18]],[5,771,58],[-440.166,-220,0,0,0,0,1,1,1,1]],[0,"04 white",1,[[1,-19,[14],15],[2,2,-20,16,17],[11,-21]],[5,596,56],[-527.386,-310,0,0,0,0,1,1,1,1]],[0,"05 white",1,[[1,-22,[18],19],[2,2,-23,20,21],[12,-24]],[5,537,57],[-555,-400,0,0,0,0,1,1,1,1]],[13,"New Node",[1],[0,0,0],[0,0,0,0,0,0,1,1,1,1]],[5,"Main Camera",1,[[14,7,-25]],[5,960,640]],[0,"01beijing",1,[[1,-26,[0],1]],[5,1920,1080],[-1.616,0.067,0,0,0,0,1,1,1,1]]],0,[0,0,1,0,0,1,0,-1,8,0,-2,9,0,-3,2,0,-4,3,0,-5,4,0,-6,5,0,-7,6,0,0,2,0,0,2,0,0,2,0,0,3,0,0,3,0,0,3,0,0,4,0,0,4,0,0,4,0,0,5,0,0,5,0,0,5,0,0,6,0,0,6,0,0,6,0,0,8,0,0,9,0,5,7,1,6,7,26],[0,0,0,0,0,0,0,0,0,0,0,0,0,0,0,0,0,0,0,0,0,0],[-1,2,-1,2,3,4,-1,2,3,4,-1,2,3,4,-1,2,3,4,-1,2,3,4],[0,7,0,1,1,8,0,2,2,9,0,3,3,10,0,4,4,11,0,5,5,12]],[[{"name":"03 white","rect":[214,171,771,58],"offset":[-360.5,0],"originalSize":[1920,400],"capInsets":[0,0,0,0]}],[0],0,[0],[1],[13]],[[{"name":"05 green","rect":[214,172,537,57],"offset":[-477.5,-0.5],"originalSize":[1920,400],"capInsets":[0,0,0,0]}],[0],0,[0],[1],[14]],[[{"name":"02 white","rect":[214,171,713,58],"offset":[-389.5,0],"originalSize":[1920,400],"capInsets":[0,0,0,0]}],[0],0,[0],[1],[15]],[[{"name":"03 green","rect":[214,171,771,58],"offset":[-360.5,0],"originalSize":[1920,400],"capInsets":[0,0,0,0]}],[0],0,[0],[1],[16]],[[{"name":"05 white","rect":[214,172,537,57],"offset":[-477.5,-0.5],"originalSize":[1920,400],"capInsets":[0,0,0,0]}],[0],0,[0],[1],[17]],[[{"name":"01 green","rect":[214,171,771,58],"offset":[-360.5,0],"originalSize":[1920,400],"capInsets":[0,0,0,0]}],[0],0,[0],[1],[18]],[[{"name":"01beijing","rect":[0,0,1920,1080],"offset":[0,0],"originalSize":[1920,1080],"capInsets":[0,0,0,0]}],[0],0,[0],[1],[19]],[[{"name":"02 green","rect":[214,171,713,58],"offset":[-389.5,0],"originalSize":[1920,400],"capInsets":[0,0,0,0]}],[0],0,[0],[1],[20]],[[{"name":"01 white","rect":[214,171,771,58],"offset":[-360.5,0],"originalSize":[1920,400],"capInsets":[0,0,0,0]}],[0],0,[0],[1],[21]],[[{"name":"04 green","rect":[214,172,596,56],"offset":[-448,0],"originalSize":[1920,400],"capInsets":[0,0,0,0]}],[0],0,[0],[1],[22]]]]